{
    "games": [
      {
        "id": 1,
        "img": "../../../../assets/img/games-catalog/half-life2.jpeg",
        "name": "Half Life 2",
        "company": "Valve",
        "category": "Shooter",
        "requirements": {
          "cpu": "Intel i5",
          "ram": "8GB",
          "gpu": "Nvidia GTX1080",
          "os": "Windows XP"
        },
        "price": 5000
      },
      {
        "id": 2,
        "img": "../../../../assets/img/games-catalog/red-dead-redemption.jpeg",
        "name": "Red Dead Redemption 2",
        "company": "Rockstar Games",
        "category": "Shooter",
        "requirements": {
          "cpu": "Intel i7",
          "ram": "8GB",
          "gpu": "Nvidia RTX3050",
          "os": "Windows 10"
        },
        "price": 10000
      }
    ]
  }
  